Embedding/EmbeddingProvider.py
Embedding/__init__.py
Generation/AnswerGenerator.py
Generation/DocumentRetriever.py
Generation/RAGGenerationPipeline.py
Generation/__init__.py
HallucinationsCheck/HallucinationsCheck.py
HallucinationsCheck/__init__.py
LLMProvider/LLMProvider.py
LLMProvider/__init__.py
Muffakir/Enums.py
Muffakir/Muffakir.py
Muffakir/MuffakirSearch.py
Muffakir/MuffakirSyntheticData.py
Muffakir/Search.py
Muffakir/SyntheticData.py
Muffakir/__init__.py
Muffakir/config.py
PromptManager/PromptManager.py
PromptManager/__init__.py
QueryTransformer/QueryTransformer.py
QueryTransformer/__init__.py
RAGPipeline/RAGPipelineManager.py
RAGPipeline/RetrieveMethods.py
RAGPipeline/__init__.py
Reranker/Reranker.py
Reranker/__init__.py
TextProcessor/ChunkingAndProcessing.py
TextProcessor/__init__.py
VectorDB/ChromaDBManager.py
VectorDB/__init__.py
Muffakir-0.1.6.dist-info/METADATA
Muffakir-0.1.6.dist-info/WHEEL
Muffakir-0.1.6.dist-info/top_level.txt
Muffakir-0.1.6.dist-info/RECORD
