Metadata-Version: 2.1
Name: Muffakir
Version: 0.1.6
Summary: Arabic Retrieval-Augmented Generation Library
Home-page: UNKNOWN
Author: Mohamed
License: UNKNOWN
Platform: UNKNOWN
Requires-Python: >=3.8
Requires-Dist: azure-ai-formrecognizer (==3.3.3)
Requires-Dist: chromadb (==0.6.3)
Requires-Dist: fastembed (==0.5.1)
Requires-Dist: langchain (==0.3.17)
Requires-Dist: langchain-chroma (==0.2.1)
Requires-Dist: langchain-community (==0.3.16)
Requires-Dist: langchain-openai (==0.3.3)
Requires-Dist: langchain-groq (==0.2.4)
Requires-Dist: nltk (==3.9.1)
Requires-Dist: rank-bm25 (==0.2.2)
Requires-Dist: sentence-transformers (==3.4.1)
Requires-Dist: tiktoken (==0.8.0)
Requires-Dist: transformers (==4.48.2)
Requires-Dist: unstructured[pdf] (==0.16.17)
Requires-Dist: pydantic (==2.11.3)
Requires-Dist: python-dotenv (==1.0.1)
Requires-Dist: pydantic-settings (==2.7.1)
Requires-Dist: spacy (==3.8.7)
